MANIFEST.in
README.rst
setup.py
rpi_rf_gpiod/__init__.py
rpi_rf_gpiod/rpi_rf_gpiod.py
rpi_rf_gpiod.egg-info/PKG-INFO
rpi_rf_gpiod.egg-info/SOURCES.txt
rpi_rf_gpiod.egg-info/dependency_links.txt
rpi_rf_gpiod.egg-info/top_level.txt
scripts/rpi-rf_receive
scripts/rpi-rf_send