Metadata-Version: 1.1
Name: rpi-rf-gpiod
Version: 0.1.0
Summary: Sending and receiving 433/315MHz signals with low-cost GPIO RF modules on a Raspberry Pi accessed with gpiod
Home-page: https://github.com/aoertel/rpi-rf-gpiod
Author: Andy Oertel
Author-email: oertelandy@gmail.com
License: BSD
Keywords: rpi,raspberry,raspberry pi,rf,gpio,radio,433,433mhz,315,315mhz,gpiod,libgpiod,libgpiod-python
Platform: UNKNOWN
Classifier: Development Status :: 4 - Beta
Classifier: Intended Audience :: Developers
Classifier: Topic :: Software Development :: Build Tools
Classifier: License :: OSI Approved :: BSD License
Classifier: Programming Language :: Python :: 3
Classifier: Operating System :: POSIX :: Linux
Classifier: Topic :: Software Development :: Libraries :: Python Modules
